fastcc/__init__.py
fastcc/cli.py
fastcc/auth/__init__.py
fastcc/auth/oauth.py
fastcc/core/__init__.py
fastcc/core/config.py
fastcc/core/endpoint.py
fastcc/core/endpoint_group.py
fastcc/core/endpoint_group_manager.py
fastcc/core/error_classifier.py
fastcc/core/models.py
fastcc/core/priority_manager.py
fastcc/providers/__init__.py
fastcc/providers/browser.py
fastcc/providers/manager.py
fastcc/proxy/__init__.py
fastcc/proxy/circuit_breaker.py
fastcc/proxy/conversational_checker.py
fastcc/proxy/failover_manager.py
fastcc/proxy/failure_queue.py
fastcc/proxy/health_check_models.py
fastcc/proxy/health_monitor.py
fastcc/proxy/load_balancer.py
fastcc/proxy/performance_metrics.py
fastcc/proxy/server.py
fastcc/proxy/session_affinity.py
fastcc/proxy/weight_adjuster.py
fastcc/storage/__init__.py
fastcc/storage/base.py
fastcc/storage/cloud_file.py
fastcc/storage/github_gist.py
fastcc/storage/github_simple.py
fastcc/storage/jsonbin.py
fastcc/storage/pastebin.py
fastcc/storage/simple_http.py
fastcc/utils/__init__.py
fastcc/utils/crypto.py
fastcc/utils/ui.py
fastcc/web/__init__.py
fastcc/web/app.py
fastcc/web/models.py
fastcc/web/utils.py
fastcc/web/routers/__init__.py
fastcc/web/routers/claude_config.py
fastcc/web/routers/configs.py
fastcc/web/routers/dashboard.py
fastcc/web/routers/endpoints.py
fastcc/web/routers/health.py
fastcc/web/routers/priority.py
fastcc/web/routers/proxy.py
fastcc/web/routers/queue.py
fastcc/web/routers/system.py
fastcc/web/static/index.html
fastcc/web/static/vite.svg
fastcc/web/static/assets/index-DU0t6CeV.css
fastcc/web/static/assets/index-SA-czMe6.js
qcc-0.6.1.dist-info/METADATA
qcc-0.6.1.dist-info/WHEEL
qcc-0.6.1.dist-info/entry_points.txt
qcc-0.6.1.dist-info/RECORD
