Metadata-Version: 2.4
Name: qcc
Version: 0.6.1
Summary: 🚀 现代化 Claude Code 配置管理神器 - 零配置启动，多端同步，安全加密，厂商快速配置
Project-URL: Homepage, https://github.com/lghguge520/qcc
Project-URL: Repository, https://github.com/lghguge520/qcc.git
Project-URL: Issues, https://github.com/lghguge520/qcc/issues
Author: QCC Team
License-Expression: MIT
Keywords: ai,anthropic,claude,cli,config,fast-config,provider,proxy,qcc
Classifier: Development Status :: 4 - Beta
Classifier: Intended Audience :: Developers
Classifier: License :: OSI Approved :: MIT License
Classifier: Operating System :: OS Independent
Classifier: Programming Language :: Python :: 3
Classifier: Programming Language :: Python :: 3.9
Classifier: Programming Language :: Python :: 3.10
Classifier: Programming Language :: Python :: 3.11
Classifier: Programming Language :: Python :: 3.12
Classifier: Topic :: Software Development
Classifier: Topic :: Utilities
Requires-Python: >=3.9
Requires-Dist: aiohttp-cors>=0.7.0
Requires-Dist: aiohttp>=3.8.0
Requires-Dist: click>=8.0.0
Requires-Dist: cryptography>=3.4.0
Requires-Dist: fastapi>=0.100.0
Requires-Dist: httpx>=0.25.0
Requires-Dist: prompt-toolkit>=3.0.0
Requires-Dist: psutil>=5.9.0
Requires-Dist: pydantic>=2.0.0
Requires-Dist: requests>=2.25.0
Requires-Dist: rich>=12.0.0
Requires-Dist: tenacity>=8.0.0
Requires-Dist: uvicorn[standard]>=0.23.0
Provides-Extra: dev
Requires-Dist: black; extra == 'dev'
Requires-Dist: flake8; extra == 'dev'
Requires-Dist: mypy; extra == 'dev'
Requires-Dist: pytest>=6.0; extra == 'dev'
Provides-Extra: web
Requires-Dist: fastapi>=0.100.0; extra == 'web'
Requires-Dist: uvicorn[standard]>=0.23.0; extra == 'web'
